{"otherData": {},"traceEvents":[{"cat":"function","dur":132946,"name":"glfwInit","ph":"X","pid":0,"tid":952477563,"ts":60746502060},{"cat":"function","dur":671517,"name":"glfwCreateWindow","ph":"X","pid":0,"tid":952477563,"ts":60746635164},{"cat":"function","dur":5082,"name":"void __cdecl Hazel::OpenGLContext::Init(void)","ph":"X","pid":0,"tid":952477563,"ts":60747306840},{"cat":"function","dur":84,"name":"void __cdecl Hazel::WindowsWindow::SetVSync(bool)","ph":"X","pid":0,"tid":952477563,"ts":60747312074},{"cat":"function","dur":811273,"name":"void __cdecl Hazel::WindowsWindow::Init(const struct Hazel::WindowProps &)","ph":"X","pid":0,"tid":952477563,"ts":60746500934},{"cat":"function","dur":811311,"name":"__cdecl Hazel::WindowsWindow::WindowsWindow(const struct Hazel::WindowProps &)","ph":"X","pid":0,"tid":952477563,"ts":60746500934},{"cat":"function","dur":13,"name":"void __cdecl Hazel::OpenGLRendererAPI::Init(void)","ph":"X","pid":0,"tid":952477563,"ts":60747312298},{"cat":"function","dur":51,"name":"__cdecl Hazel::OpenGLVertexArray::OpenGLVertexArray(void)","ph":"X","pid":0,"tid":952477563,"ts":60747312358},{"cat":"function","dur":27,"name":"__cdecl Hazel::OpenGLVertexBuffer::OpenGLVertexBuffer(unsigned int)","ph":"X","pid":0,"tid":952477563,"ts":60747312468},{"cat":"function","dur":0,"name":"void __cdecl Hazel::OpenGLVertexBuffer::Bind(void) const","ph":"X","pid":0,"tid":952477563,"ts":60747312610},{"cat":"function","dur":92,"name":"void __cdecl Hazel::OpenGLVertexArray::AddVertexBuffer(const class std::shared_ptr<class Hazel::VertexBuffer> &)","ph":"X","pid":0,"tid":952477563,"ts":60747312567},{"cat":"function","dur":32,"name":"__cdecl Hazel::OpenGLIndexBuffer::OpenGLIndexBuffer(unsigned int *,unsigned int)","ph":"X","pid":0,"tid":952477563,"ts":60747312699},{"cat":"function","dur":0,"name":"void __cdecl Hazel::OpenGLIndexBuffer::Bind(void) const","ph":"X","pid":0,"tid":952477563,"ts":60747312773},{"cat":"function","dur":36,"name":"void __cdecl Hazel::OpenGLVertexArray::SetIndexBuffer(const class std::shared_ptr<class Hazel::IndexBuffer> &)","ph":"X","pid":0,"tid":952477563,"ts":60747312772},{"cat":"function","dur":530,"name":"__cdecl Hazel::OpenGLTexture2D::OpenGLTexture2D(unsigned int,unsigned int)","ph":"X","pid":0,"tid":952477563,"ts":60747312849},{"cat":"function","dur":12,"name":"void __cdecl Hazel::OpenGLTexture2D::SetData(void *,unsigned int)","ph":"X","pid":0,"tid":952477563,"ts":60747313443},{"cat":"function","dur":453,"name":"class std::basic_string<char,struct std::char_traits<char>,class std::allocator<char> > __cdecl Hazel::OpenGLShader::ReadFile(const class std::basic_string<char,struct std::char_traits<char>,class std::allocator<char> > &)","ph":"X","pid":0,"tid":952477563,"ts":60747313502},{"cat":"function","dur":64,"name":"class std::unordered_map<unsigned int,class std::basic_string<char,struct std::char_traits<char>,class std::allocator<char> >,struct std::hash<unsigned int>,struct std::equal_to<unsigned int>,class std::allocator<struct std::pair<unsigned int const ,class std::basic_string<char,struct std::char_traits<char>,class std::allocator<char> > > > > __cdecl Hazel::OpenGLShader::PreProcess(const class std::basic_string<char,struct std::char_traits<char>,class std::allocator<char> > &)","ph":"X","pid":0,"tid":952477563,"ts":60747314029},{"cat":"function","dur":986,"name":"void __cdecl Hazel::OpenGLShader::Compile(class std::unordered_map<unsigned int,class std::basic_string<char,struct std::char_traits<char>,class std::allocator<char> >,struct std::hash<unsigned int>,struct std::equal_to<unsigned int>,class std::allocator<struct std::pair<unsigned int const ,class std::basic_string<char,struct std::char_traits<char>,class std::allocator<char> > > > >)","ph":"X","pid":0,"tid":952477563,"ts":60747314145},{"cat":"function","dur":1770,"name":"__cdecl Hazel::OpenGLShader::OpenGLShader(const class std::basic_string<char,struct std::char_traits<char>,class std::allocator<char> > &)","ph":"X","pid":0,"tid":952477563,"ts":60747313500},{"cat":"function","dur":3,"name":"void __cdecl Hazel::OpenGLShader::Bind(void) const","ph":"X","pid":0,"tid":952477563,"ts":60747315309},{"cat":"function","dur":54,"name":"void __cdecl Hazel::OpenGLShader::SetIntArray(const class std::basic_string<char,struct std::char_traits<char>,class std::allocator<char> > &,int *,unsigned int)","ph":"X","pid":0,"tid":952477563,"ts":60747315406},{"cat":"function","dur":3157,"name":"void __cdecl Hazel::Renderer2D::Init(void)","ph":"X","pid":0,"tid":952477563,"ts":60747312348},{"cat":"function","dur":3235,"name":"void __cdecl Hazel::Renderer::Init(void)","ph":"X","pid":0,"tid":952477563,"ts":60747312297},{"cat":"function","dur":6635,"name":"void __cdecl Hazel::ImGuiLayer::OnAttach(void)","ph":"X","pid":0,"tid":952477563,"ts":60747315567},{"cat":"function","dur":6763,"name":"void __cdecl Hazel::Application::PushOverlay(class Hazel::Layer *)","ph":"X","pid":0,"tid":952477563,"ts":60747315561},{"cat":"function","dur":821425,"name":"__cdecl Hazel::Application::Application(const class std::basic_string<char,struct std::char_traits<char>,class std::allocator<char> > &)","ph":"X","pid":0,"tid":952477563,"ts":60746500929},{"cat":"function","dur":5,"name":"__cdecl Hazel::OrthographicCamera::OrthographicCamera(float,float,float,float)","ph":"X","pid":0,"tid":952477563,"ts":60747322397},{"cat":"function","dur":599,"name":"stbi_load - OpenGLTexture2D::OpenGLTexture2D(const std::string&)","ph":"X","pid":0,"tid":952477563,"ts":60747322449},{"cat":"function","dur":878,"name":"__cdecl Hazel::OpenGLTexture2D::OpenGLTexture2D(const class std::basic_string<char,struct std::char_traits<char>,class std::allocator<char> > &)","ph":"X","pid":0,"tid":952477563,"ts":60747322445},{"cat":"function","dur":3920,"name":"void __cdecl Hazel::EditorLayer::OnAttach(void)","ph":"X","pid":0,"tid":952477563,"ts":60747322440},{"cat":"function","dur":4066,"name":"void __cdecl Hazel::Application::PushLayer(class Hazel::Layer *)","ph":"X","pid":0,"tid":952477563,"ts":60747322431}]}